[
    { "id": 1, "name": "John Doe", "age": 30, "occupation": "Software Engineer" },
    { "id": 2, "name": "Jane Smith", "age": 25, "occupation": "Graphic Designer" },
    { "id": 3, "name": "Emily Johnson", "age": 40, "occupation": "Project Manager" },
    { "id": 4, "name": "Michael Brown", "age": 35, "occupation": "Data Scientist" },
    { "id": 5, "name": "Sarah Williams", "age": 28, "occupation": "Marketing Specialist" },
    { "id": 6, "name": "David Wilson", "age": 32, "occupation": "Web Developer" },
    { "id": 7, "name": "Laura Garcia", "age": 27, "occupation": "Product Designer" },
    { "id": 8, "name": "Kevin Martinez", "age": 45, "occupation": "Financial Analyst" },
    { "id": 9, "name": "Sophia Lee", "age": 29, "occupation": "HR Specialist" },
    { "id": 10, "name": "Chris Kim", "age": 33, "occupation": "Operations Manager" },
    { "id": 11, "name": "Jessica Turner", "age": 26, "occupation": "Content Writer" },
    { "id": 12, "name": "Matthew Hill", "age": 36, "occupation": "Sales Manager" },
    { "id": 13, "name": "Lisa Scott", "age": 31, "occupation": "UI/UX Designer" },
    { "id": 14, "name": "Robert Adams", "age": 38, "occupation": "IT Consultant" },
    { "id": 15, "name": "Olivia Nelson", "age": 24, "occupation": "Accountant" },
    { "id": 16, "name": "James Carter", "age": 42, "occupation": "Business Analyst" },
    { "id": 17, "name": "Megan Evans", "age": 34, "occupation": "Architect" },
    { "id": 18, "name": "Brian Walker", "age": 28, "occupation": "Mechanical Engineer" },
    { "id": 19, "name": "Chloe Harris", "age": 27, "occupation": "Social Media Manager" },
    { "id": 20, "name": "Daniel Thompson", "age": 39, "occupation": "Real Estate Agent" },
    { "id": 21, "name": "Ava White", "age": 23, "occupation": "Customer Support Specialist" },
    { "id": 22, "name": "Ethan Green", "age": 37, "occupation": "Electrical Engineer" },
    { "id": 23, "name": "Grace Lewis", "age": 29, "occupation": "Clinical Researcher" },
    { "id": 24, "name": "Jacob Young", "age": 33, "occupation": "Data Analyst" },
    { "id": 25, "name": "Abigail Allen", "age": 41, "occupation": "Marketing Manager" },
    { "id": 26, "name": "Elijah Hernandez", "age": 35, "occupation": "Pharmacist" },
    { "id": 27, "name": "Charlotte King", "age": 32, "occupation": "Teacher" },
    { "id": 28, "name": "Michael Rivera", "age": 40, "occupation": "Veterinarian" },
    { "id": 29, "name": "Samantha Morgan", "age": 27, "occupation": "Paralegal" },
    { "id": 30, "name": "Alexander Perez", "age": 34, "occupation": "Software Tester" },
    { "id": 40, "name": "Emma Mitchell", "age": 29, "occupation": "Copywriter" },
    { "id": 41, "name": "Liam Brooks", "age": 43, "occupation": "Physician" },
    { "id": 42, "name": "Amelia Reed", "age": 27, "occupation": "Therapist" },
    { "id": 43, "name": "Noah Ward", "age": 36, "occupation": "Sales Consultant" },
    { "id": 44, "name": "Mia Bailey", "age": 32, "occupation": "Chef" },
    { "id": 45, "name": "Lucas Sanders", "age": 40, "occupation": "Economist" },
    { "id": 46, "name": "Harper Butler", "age": 24, "occupation": "Interior Designer" },
    { "id": 47, "name": "Henry Foster", "age": 31, "occupation": "Civil Engineer" },
    { "id": 48, "name": "Avery Gonzales", "age": 39, "occupation": "Nutritionist" },
    { "id": 49, "name": "Ella Collins", "age": 30, "occupation": "Journalist" },
    { "id": 50, "name": "Jack Gray", "age": 37, "occupation": "Investment Banker" },
    { "id": 51, "name": "Lily Patterson", "age": 26, "occupation": "Physiotherapist" },
    { "id": 52, "name": "Owen Hughes", "age": 45, "occupation": "Graphic Artist" },
    { "id": 53, "name": "Zoe Price", "age": 33, "occupation": "Biomedical Engineer" },
    { "id": 54, "name": "Samuel Flores", "age": 38, "occupation": "Environmental Scientist" },
    { "id": 55, "name": "Leah Powell", "age": 29, "occupation": "Fashion Designer" },
    { "id": 56, "name": "Isaac Ross", "age": 41, "occupation": "Technical Writer" },
    { "id": 57, "name": "Sofia Jenkins", "age": 28, "occupation": "Software Developer" },
    { "id": 58, "name": "Benjamin Rivera", "age": 35, "occupation": "Cybersecurity Analyst" },
    { "id": 59, "name": "Emily Long", "age": 42, "occupation": "Psychiatrist" },
    { "id": 60, "name": "Michael Ramirez", "age": 44, "occupation": "Construction Manager" },
    { "id": 61, "name": "Aria Hall", "age": 25, "occupation": "Librarian" },
    { "id": 62, "name": "Elijah Scott", "age": 34, "occupation": "Chemical Engineer" },
    { "id": 63, "name": "Grace Lewis", "age": 30, "occupation": "Bank Teller" },
    { "id": 64, "name": "Sebastian Russell", "age": 29, "occupation": "Dentist" },
    { "id": 65, "name": "Madison Cox", "age": 39, "occupation": "Botanist" },
    { "id": 66, "name": "James Diaz", "age": 31, "occupation": "AI Specialist" },
    { "id": 67, "name": "Victoria Perez", "age": 32, "occupation": "Legal Advisor" },
    { "id": 68, "name": "Andrew Richardson", "age": 34, "occupation": "Event Planner" },
    { "id": 69, "name": "Ella Myers", "age": 40, "occupation": "Anthropologist" },
    { "id": 70, "name": "Logan Murphy", "age": 28, "occupation": "Geologist" },
    { "id": 71, "name": "Hannah Perry", "age": 27, "occupation": "Marine Biologist" },
    { "id": 72, "name": "Nathan Rivera", "age": 43, "occupation": "Historian" },
    { "id": 73, "name": "Lillian Martinez", "age": 35, "occupation": "Digital Marketer" },
    { "id": 74, "name": "Carter Alexander", "age": 26, "occupation": "Pilot" },
    { "id": 75, "name": "Abigail Brooks", "age": 33, "occupation": "Veterinary Technician" },
    { "id": 76, "name": "Jackson Thompson", "age": 38, "occupation": "Air Traffic Controller" },
    { "id": 77, "name": "Chloe Young", "age": 30, "occupation": "Dietitian" },
    { "id": 78, "name": "Luke Hernandez", "age": 41, "occupation": "Photographer" },
    { "id": 79, "name": "Samantha Cooper", "age": 36, "occupation": "Counselor" },
    { "id": 80, "name": "Alexander Edwards", "age": 37, "occupation": "Musician" },
    { "id": 81, "name": "Zoey Rogers", "age": 29, "occupation": "Real Estate Broker" },
    { "id": 82, "name": "Christian Barnes", "age": 35, "occupation": "Film Producer" },
    { "id": 83, "name": "Sadie Morgan", "age": 42, "occupation": "Nurse" },
    { "id": 84, "name": "Dylan Reed", "age": 39, "occupation": "Electrician" },
    { "id": 85, "name": "Brooklyn Bell", "age": 28, "occupation": "Journalist" },
    { "id": 86, "name": "Mason Griffin", "age": 33, "occupation": "Logistics Specialist" },
    { "id": 87, "name": "Elizabeth James", "age": 27, "occupation": "Personal Trainer" },
    { "id": 88, "name": "Aiden Russell", "age": 34, "occupation": "Chef" },
    { "id": 89, "name": "Scarlett Peterson", "age": 26, "occupation": "Social Worker" },
    { "id": 90, "name": "Joshua Miller", "age": 29, "occupation": "Lawyer" },
    { "id": 91, "name": "Bella Clark", "age": 41, "occupation": "Animator" },
    { "id": 92, "name": "Isaac Martinez", "age": 32, "occupation": "Systems Administrator" },
    { "id": 93, "name": "Evelyn Stewart", "age": 30, "occupation": "PR Specialist" },
    { "id": 94, "name": "Daniel Ward", "age": 37, "occupation": "Political Analyst" },
    { "id": 95, "name": "Penelope Campbell", "age": 43, "occupation": "Architect" },
    { "id": 96, "name": "David Powell", "age": 40, "occupation": "Chef" },
    { "id": 97, "name": "Sophia Hayes", "age": 34, "occupation": "Chemist" },
    { "id": 98, "name": "Elijah Jenkins", "age": 26, "occupation": "Geographer" },
    { "id": 99, "name": "Isabella Evans", "age": 28, "occupation": "Meteorologist" },
    { "id": 100, "name": "Henry Foster", "age": 29, "occupation": "Statistician" }
]

